{"articleId_2513.jpg":"http://jwzx.hrbust.edu.cn/homepage/infoSingleArticle.do?articleId=2513&columnId=354","articleId_2512.jpg":"http://jwzx.hrbust.edu.cn/homepage/infoSingleArticle.do?articleId=2512&columnId=354","articleId_2511.jpg":"http://jwzx.hrbust.edu.cn/homepage/infoSingleArticle.do?articleId=2511&columnId=354","articleId_2510.jpg":"http://jwzx.hrbust.edu.cn/homepage/infoSingleArticle.do?articleId=2510&columnId=354","articleId_2509.jpg":"http://jwzx.hrbust.edu.cn/homepage/infoSingleArticle.do?articleId=2509&columnId=354","articleId_2507.jpg":"http://jwzx.hrbust.edu.cn/homepage/infoSingleArticle.do?articleId=2507&columnId=354","articleId_2505.jpg":"http://jwzx.hrbust.edu.cn/homepage/infoSingleArticle.do?articleId=2505&columnId=354","articleId_2504.jpg":"http://jwzx.hrbust.edu.cn/homepage/infoSingleArticle.do?articleId=2504&columnId=354","articleId_2503.jpg":"http://jwzx.hrbust.edu.cn/homepage/infoSingleArticle.do?articleId=2503&columnId=354","articleId_2501.jpg":"http://jwzx.hrbust.edu.cn/homepage/infoSingleArticle.do?articleId=2501&columnId=354","articleId_2500.jpg":"http://jwzx.hrbust.edu.cn/homepage/infoSingleArticle.do?articleId=2500&columnId=354","articleId_2498.jpg":"http://jwzx.hrbust.edu.cn/homepage/infoSingleArticle.do?articleId=2498&columnId=354","articleId_2519.jpg":"http://jwzx.hrbust.edu.cn/homepage/infoSingleArticle.do?articleId=2519&columnId=354","articleId_2515.jpg":"http://jwzx.hrbust.edu.cn/homepage/infoSingleArticle.do?articleId=2515&columnId=354","articleId_2508.jpg":"http://jwzx.hrbust.edu.cn/homepage/infoSingleArticle.do?articleId=2508&columnId=354","articleId_2472.jpg":"http://jwzx.hrbust.edu.cn/homepage/infoSingleArticle.do?articleId=2472&columnId=354","articleId_2524.jpg":"http://jwzx.hrbust.edu.cn/homepage/infoSingleArticle.do?articleId=2524&columnId=354","articleId_2523.jpg":"http://jwzx.hrbust.edu.cn/homepage/infoSingleArticle.do?articleId=2523&columnId=354","articleId_2522.jpg":"http://jwzx.hrbust.edu.cn/homepage/infoSingleArticle.do?articleId=2522&columnId=354","articleId_2520.jpg":"http://jwzx.hrbust.edu.cn/homepage/infoSingleArticle.do?articleId=2520&columnId=354","articleId_2518.jpg":"http://jwzx.hrbust.edu.cn/homepage/infoSingleArticle.do?articleId=2518&columnId=354","articleId_2517.jpg":"http://jwzx.hrbust.edu.cn/homepage/infoSingleArticle.do?articleId=2517&columnId=354","articleId_2516.jpg":"http://jwzx.hrbust.edu.cn/homepage/infoSingleArticle.do?articleId=2516&columnId=354","articleId_2514.jpg":"http://jwzx.hrbust.edu.cn/homepage/infoSingleArticle.do?articleId=2514&columnId=354","articleId_2497.jpg":"http://jwzx.hrbust.edu.cn/homepage/infoSingleArticle.do?articleId=2497&columnId=354","articleId_2496.jpg":"http://jwzx.hrbust.edu.cn/homepage/infoSingleArticle.do?articleId=2496&columnId=354","articleId_2494.jpg":"http://jwzx.hrbust.edu.cn/homepage/infoSingleArticle.do?articleId=2494&columnId=354","articleId_2493.jpg":"http://jwzx.hrbust.edu.cn/homepage/infoSingleArticle.do?articleId=2493&columnId=354","articleId_2492.jpg":"http://jwzx.hrbust.edu.cn/homepage/infoSingleArticle.do?articleId=2492&columnId=354","articleId_2484.jpg":"http://jwzx.hrbust.edu.cn/homepage/infoSingleArticle.do?articleId=2484&columnId=354","articleId_2491.jpg":"http://jwzx.hrbust.edu.cn/homepage/infoSingleArticle.do?articleId=2491&columnId=354","articleId_2488.jpg":"http://jwzx.hrbust.edu.cn/homepage/infoSingleArticle.do?articleId=2488&columnId=354","articleId_2487.jpg":"http://jwzx.hrbust.edu.cn/homepage/infoSingleArticle.do?articleId=2487&columnId=354","articleId_2483.jpg":"http://jwzx.hrbust.edu.cn/homepage/infoSingleArticle.do?articleId=2483&columnId=354","articleId_2482.jpg":"http://jwzx.hrbust.edu.cn/homepage/infoSingleArticle.do?articleId=2482&columnId=354","articleId_2479.jpg":"http://jwzx.hrbust.edu.cn/homepage/infoSingleArticle.do?articleId=2479&columnId=354","articleId_2477.jpg":"http://jwzx.hrbust.edu.cn/homepage/infoSingleArticle.do?articleId=2477&columnId=354","articleId_2476.jpg":"http://jwzx.hrbust.edu.cn/homepage/infoSingleArticle.do?articleId=2476&columnId=354","articleId_2475.jpg":"http://jwzx.hrbust.edu.cn/homepage/infoSingleArticle.do?articleId=2475&columnId=354","articleId_2474.jpg":"http://jwzx.hrbust.edu.cn/homepage/infoSingleArticle.do?articleId=2474&columnId=354","articleId_2473.jpg":"http://jwzx.hrbust.edu.cn/homepage/infoSingleArticle.do?articleId=2473&columnId=354","articleId_2471.jpg":"http://jwzx.hrbust.edu.cn/homepage/infoSingleArticle.do?articleId=2471&columnId=354","articleId_2470.jpg":"http://jwzx.hrbust.edu.cn/homepage/infoSingleArticle.do?articleId=2470&columnId=354","articleId_2469.jpg":"http://jwzx.hrbust.edu.cn/homepage/infoSingleArticle.do?articleId=2469&columnId=354","articleId_2468.jpg":"http://jwzx.hrbust.edu.cn/homepage/infoSingleArticle.do?articleId=2468&columnId=354","articleId_2467.jpg":"http://jwzx.hrbust.edu.cn/homepage/infoSingleArticle.do?articleId=2467&columnId=354","articleId_2466.jpg":"http://jwzx.hrbust.edu.cn/homepage/infoSingleArticle.do?articleId=2466&columnId=354","articleId_2465.jpg":"http://jwzx.hrbust.edu.cn/homepage/infoSingleArticle.do?articleId=2465&columnId=354"}